forza/__init__.py
forza/core.py
forza/lightspeed.py
forza/modules/__init__.py
forza/modules/inputs.py
forza/modules/loaders.py
forza/modules/text.py
forza-0.0.1.dist-info/METADATA
forza-0.0.1.dist-info/WHEEL
forza-0.0.1.dist-info/top_level.txt
forza-0.0.1.dist-info/RECORD
