Metadata-Version: 2.1
Name: forza
Version: 0.0.1
Summary: forza
Author: Hammad Saeed
Author-email: hammad@supportvectors.com
Classifier: Programming Language :: Python :: 3
Classifier: License :: OSI Approved :: MIT License
Classifier: Operating System :: OS Independent
Requires-Python: >3.9
Requires-Dist: art
Requires-Dist: libhammadpy-text
Requires-Dist: prompt-toolkit
Requires-Dist: wcwidth
Provides-Extra: ml
Requires-Dist: suzuka ; extra == 'ml'
